scl/__init__.py
scl/aug.py
scl/imagenet_eval.py
scl/scl.py
scl/stl10_eval.py
scl/utils.py
scl/custom_datasets/__init__.py
scl/custom_datasets/custom_datasets.py
scl/custom_datasets/huggingface_dataset.py
scl/encoders/__init__.py
scl/encoders/models.py
sigmoid_contrastive_learning-0.1.0.dist-info/LICENSE
sigmoid_contrastive_learning-0.1.0.dist-info/METADATA
sigmoid_contrastive_learning-0.1.0.dist-info/WHEEL
sigmoid_contrastive_learning-0.1.0.dist-info/entry_points.txt
sigmoid_contrastive_learning-0.1.0.dist-info/top_level.txt
sigmoid_contrastive_learning-0.1.0.dist-info/RECORD
